skill_core_ready/LICENSE.md
skill_core_ready/README.md
skill_core_ready/__init__.py
skill_core_ready/skill.json
skill_core_ready/version.py
skill_core_ready/locale/en-us/dialog/confirm_no_speak_ready.dialog
skill_core_ready/locale/en-us/dialog/confirm_speak_ready.dialog
skill_core_ready/locale/en-us/dialog/ready.dialog
skill_core_ready/locale/en-us/intent/disable_ready_notification.intent
skill_core_ready/locale/en-us/intent/enable_ready_notification.intent
skill_core_ready/neon_skill_core_ready.egg-info/PKG-INFO
skill_core_ready/neon_skill_core_ready.egg-info/SOURCES.txt
skill_core_ready/neon_skill_core_ready.egg-info/dependency_links.txt
skill_core_ready/neon_skill_core_ready.egg-info/entry_points.txt
skill_core_ready/neon_skill_core_ready.egg-info/requires.txt
skill_core_ready/neon_skill_core_ready.egg-info/top_level.txt
skill_core_ready/test/test_skill.py
neon_skill_core_ready-0.2.0.dist-info/LICENSE.md
neon_skill_core_ready-0.2.0.dist-info/METADATA
neon_skill_core_ready-0.2.0.dist-info/WHEEL
neon_skill_core_ready-0.2.0.dist-info/entry_points.txt
neon_skill_core_ready-0.2.0.dist-info/top_level.txt
neon_skill_core_ready-0.2.0.dist-info/RECORD
