Metadata-Version: 2.1
Name: neon-skill-core-ready
Version: 0.2.0
Home-page: https://github.com/NeonGeckoCom/skill-core_ready
Author: Neongecko
Author-email: developers@neon.ai
License: BSD-3-Clause
License-File: LICENSE.md
Requires-Dist: ovos-workshop>=0.0.12,~=0.0
Requires-Dist: ovos-utils>=0.0.28,~=0.0
Requires-Dist: ovos-bus-client>=0.0.3,~=0.0
Provides-Extra: test
Requires-Dist: neon-minerva[padatious]~=0.3; extra == "test"
